django_acl/__init__.py
django_acl/admin.py
django_acl/apps.py
django_acl/models.py
django_acl/tests.py
django_acl/views.py
django_acl/management/commands/init-migration.py
django_acl/management/commands/__pycache__/init-migration.cpython-310.pyc
django_acl/management/commands/__pycache__/init-process.cpython-310.pyc
django_acl/migrations/__init__.py
django_acl/utils/helper.py
django_acl/utils/__pycache__/helper.cpython-310.pyc
django_acl_permissions-2.0.0.dist-info/LICENSE.txt
django_acl_permissions-2.0.0.dist-info/METADATA
django_acl_permissions-2.0.0.dist-info/WHEEL
django_acl_permissions-2.0.0.dist-info/top_level.txt
django_acl_permissions-2.0.0.dist-info/RECORD
